anntools/__init__.py
anntools/__main__.py
anntools/py.typed
anntools/methods/__init__.py
anntools/methods/_concat.py
anntools/methods/_downsample.py
anntools/methods/_info.py
anntools/methods/_pseudobulk.py
anntools_bio-0.1.2.dist-info/METADATA
anntools_bio-0.1.2.dist-info/WHEEL
anntools_bio-0.1.2.dist-info/entry_points.txt
anntools_bio-0.1.2.dist-info/licenses/LICENSE
anntools_bio-0.1.2.dist-info/RECORD
