Metadata-Version: 2.4
Name: anntools-bio
Version: 0.1.2
Summary: A CLI-driven AnnData toolkit
Author-email: noam teyssier <22600644+noamteyssier@users.noreply.github.com>
License-File: LICENSE
Requires-Python: >=3.13
Requires-Dist: adpbulk>=0.1.4
Requires-Dist: anndata>=0.12.6
Requires-Dist: scanpy>=1.11.5
Requires-Dist: typer>=0.20.0
